spherapy/__init__.py
spherapy/__main__.py
spherapy/_version.py
spherapy/orbit.py
spherapy/timespan.py
spherapy/updater.py
spherapy/data/TLEs/25544.tle
spherapy/util/__init__.py
spherapy/util/celestrak.py
spherapy/util/constants.py
spherapy/util/credentials.py
spherapy/util/elements_u.py
spherapy/util/epoch_u.py
spherapy/util/exceptions.py
spherapy/util/orbital_u.py
spherapy/util/spacetrack.py
spherapy-0.2.1.dist-info/licenses/LICENSE.md
spherapy-0.2.1.dist-info/METADATA
spherapy-0.2.1.dist-info/WHEEL
spherapy-0.2.1.dist-info/entry_points.txt
spherapy-0.2.1.dist-info/top_level.txt
spherapy-0.2.1.dist-info/RECORD
