Metadata-Version: 2.4
Name: spherapy
Version: 0.2.1
Summary: An orbital propagator wrapper and TLE fetcher
Author-email: Robert Mearns <rz.mearns@gmail.com>
Maintainer-email: Robert Mearns <rz.mearns@gmail.com>
Project-URL: Documentation, https://rzmearns.github.io/spherapy/
Project-URL: Repository, https://github.com/rzmearns/spherapy
Project-URL: Issues, https://github.com/rzmearns/spherapy/issues
Keywords: satellite,sgp,space,orbit
Requires-Python: >=3.10
License-File: LICENSE.md
Requires-Dist: astropy==5.3.4
Requires-Dist: scipy>=1.8.0
Requires-Dist: skyfield==1.46
Requires-Dist: numpy>=1.25.2
Requires-Dist: progressbar2==4.4.1
Requires-Dist: hapsira==0.18.0
Requires-Dist: spacetrack==1.2.0
Requires-Dist: keyring>=25.0.0
Requires-Dist: platformdirs==4.3.8
Requires-Dist: importlib_resources>=6.5.2
Provides-Extra: dev
Requires-Dist: line-profiler==4.2.0; extra == "dev"
Requires-Dist: pytest==8.4.1; extra == "dev"
Requires-Dist: pytest-check==2.5.3; extra == "dev"
Requires-Dist: mypy==1.17.0; extra == "dev"
Requires-Dist: ruff==0.12.4; extra == "dev"
Requires-Dist: pre-commit==4.2.0; extra == "dev"
Requires-Dist: types-requests>=2.32.4; extra == "dev"
Requires-Dist: types-python-dateutil>=2.9.0; extra == "dev"
Dynamic: license-file
